setup.cfg
setup.py
mediasort/__init__.py
mediasort/cli.py
mediasort.egg-info/PKG-INFO
mediasort.egg-info/SOURCES.txt
mediasort.egg-info/dependency_links.txt
mediasort.egg-info/entry_points.txt
mediasort.egg-info/requires.txt
mediasort.egg-info/top_level.txt
mediasort/act/__init__.py
mediasort/act/copy_to.py
mediasort/act/plex.py
mediasort/classify/__init__.py
mediasort/classify/classification.py
mediasort/classify/imdb.py
mediasort/classify/movies.py
mediasort/classify/music.py
mediasort/classify/omdb.py
mediasort/classify/tv.py
mediasort/lib/__init__.py
mediasort/lib/validate.py